mnelab/__init__.py
mnelab/__main__.py
mnelab/dialogs/__init__.py
mnelab/dialogs/annotations.py
mnelab/dialogs/append.py
mnelab/dialogs/brainvision.py
mnelab/dialogs/calc.py
mnelab/dialogs/channel_properties.py
mnelab/dialogs/channel_stats.py
mnelab/dialogs/crop.py
mnelab/dialogs/drop_bad_epochs.py
mnelab/dialogs/epoch.py
mnelab/dialogs/erds.py
mnelab/dialogs/error_message.py
mnelab/dialogs/events.py
mnelab/dialogs/filter.py
mnelab/dialogs/find_events.py
mnelab/dialogs/history.py
mnelab/dialogs/mat.py
mnelab/dialogs/montage.py
mnelab/dialogs/npy.py
mnelab/dialogs/pick_channels.py
mnelab/dialogs/plot_evoked.py
mnelab/dialogs/psd.py
mnelab/dialogs/reference.py
mnelab/dialogs/rename_channels.py
mnelab/dialogs/run_ica.py
mnelab/dialogs/utils.py
mnelab/dialogs/xdf_chunks.py
mnelab/dialogs/xdf_metadata.py
mnelab/dialogs/xdf_streams.py
mnelab/icons/dark/actions/chan-props.svg
mnelab/icons/dark/actions/close-data.svg
mnelab/icons/dark/actions/epoch-data.svg
mnelab/icons/dark/actions/filter-data.svg
mnelab/icons/dark/actions/find-events.svg
mnelab/icons/dark/actions/open-file.svg
mnelab/icons/dark/actions/plot-data.svg
mnelab/icons/dark/actions/plot-locations.svg
mnelab/icons/dark/actions/plot-psd.svg
mnelab/icons/dark/actions/run-ica.svg
mnelab/icons/dark/actions/settings.svg
mnelab/icons/dark/actions/xdf-metadata.svg
mnelab/icons/dark/index.theme
mnelab/icons/light/actions/chan-props.svg
mnelab/icons/light/actions/close-data.svg
mnelab/icons/light/actions/epoch-data.svg
mnelab/icons/light/actions/filter-data.svg
mnelab/icons/light/actions/find-events.svg
mnelab/icons/light/actions/open-file.svg
mnelab/icons/light/actions/plot-data.svg
mnelab/icons/light/actions/plot-locations.svg
mnelab/icons/light/actions/plot-psd.svg
mnelab/icons/light/actions/run-ica.svg
mnelab/icons/light/actions/settings.svg
mnelab/icons/light/actions/xdf-metadata.svg
mnelab/icons/light/index.theme
mnelab/icons/mnelab-logo-macos.icns
mnelab/icons/mnelab-logo-macos.svg
mnelab/icons/mnelab-logo.ico
mnelab-1.0.8.dist-info/licenses/LICENSE
mnelab-1.0.8.dist-info/WHEEL
mnelab-1.0.8.dist-info/entry_points.txt
mnelab-1.0.8.dist-info/METADATA
mnelab-1.0.8.dist-info/RECORD
