Metadata-Version: 2.4
Name: mnelab
Version: 1.0.8
Summary: A graphical user interface for MNE
Keywords: EEG,MEG,MNE,GUI,electrophysiology
Author: Clemens Brunner
Author-email: Clemens Brunner <clemens.brunner@gmail.com>
License-Expression: BSD-3-Clause
License-File: LICENSE
Classifier: License :: OSI Approved :: BSD License
Classifier: Operating System :: OS Independent
Classifier: Programming Language :: Python :: 3
Classifier: Programming Language :: Python :: 3.10
Classifier: Programming Language :: Python :: 3.11
Classifier: Programming Language :: Python :: 3.12
Classifier: Programming Language :: Python :: 3.13
Classifier: Programming Language :: Python :: 3.14
Requires-Dist: edfio>=0.4.10
Requires-Dist: matplotlib>=3.8.0
Requires-Dist: mne>=1.10.2
Requires-Dist: numpy>=2.0.0
Requires-Dist: pybv>=0.7.4
Requires-Dist: pyxdf>=1.16.4
Requires-Dist: pyside6>=6.9.3,<6.10.0
Requires-Dist: scipy>=1.14.1
Requires-Dist: mkdocs-material>=9.6.14 ; extra == 'docs'
Requires-Dist: mne-qt-browser>=0.6.2 ; extra == 'full'
Requires-Dist: python-picard>=0.8.0 ; extra == 'full'
Requires-Dist: scikit-learn>=1.3.0 ; extra == 'full'
Requires-Python: >=3.10
Project-URL: changelog, https://github.com/cbrnr/mnelab/blob/main/CHANGELOG.md
Project-URL: documentation, https://mnelab.readthedocs.io/en/latest/
Project-URL: homepage, https://github.com/cbrnr/mnelab
Project-URL: repository, https://github.com/cbrnr/mnelab
Provides-Extra: docs
Provides-Extra: full
